core_flavor/__init__.py
core_flavor/apps.py
core_flavor/authentication.py
core_flavor/factories.py
core_flavor/managers.py
core_flavor/models.py
core_flavor/settings.py
core_flavor/utils.py
core_flavor/middleware/__init__.py
core_flavor/middleware/logstash.py
core_flavor/rest_framework/__init__.py
core_flavor/rest_framework/exceptions.py
core_flavor/rest_framework/fields.py
core_flavor/rest_framework/lookups.py
core_flavor/rest_framework/pagination.py
core_flavor/rest_framework/permissions.py
core_flavor/rest_framework/serializers.py
core_flavor/rest_framework/test.py
core_flavor/rest_framework/middleware/__init__.py
core_flavor/rest_framework/middleware/versioning.py
django_core_flavor-0.0.21.dist-info/DESCRIPTION.rst
django_core_flavor-0.0.21.dist-info/METADATA
django_core_flavor-0.0.21.dist-info/RECORD
django_core_flavor-0.0.21.dist-info/WHEEL
django_core_flavor-0.0.21.dist-info/metadata.json
django_core_flavor-0.0.21.dist-info/top_level.txt
