Metadata-Version: 2.0
Name: django-core-flavor
Version: 0.0.21
Summary: A Django application that provides core tools.
Home-page: https://github.com/flavors/core/
Author: mongkok
Author-email: dani.pyc@gmail.com
License: MIT
Platform: UNKNOWN
Classifier: Development Status :: 1 - Planning
Classifier: Environment :: Web Environment
Classifier: Intended Audience :: Developers
Classifier: License :: OSI Approved :: MIT License
Classifier: Operating System :: OS Independent
Classifier: Programming Language :: Python
Classifier: Programming Language :: Python :: 3
Classifier: Programming Language :: Python :: 3.4
Classifier: Programming Language :: Python :: 3.5
Classifier: Programming Language :: Python :: 3.6
Classifier: Framework :: Django
Requires-Dist: django-model-utils (>=3.0.0)
Requires-Dist: djangorestframework (>=3.5.0)
Requires-Dist: djangorestframework-jwt (>=1.11.0)
Requires-Dist: psycopg2 (>=2.6.2)
